[
  {
    "MapName": "woods",
    "MapGroups": [
      {
        "Name": "More spawns cause Woods is so slow",
        "Bots": [
          {
            "BotType": "assault",
            "MaxBotCount": 2
          },
          {
            "BotType": "sptusec",
            "MaxBotCount": 1
          },
          {
            "BotType": "assault",
            "MaxBotCount": 2
          },
          {
            "BotType": "sptbear",
            "MaxBotCount": 1
          },
          {
            "BotType": "assault",
            "MaxBotCount": 2
          },
          {
            "BotType": "assault",
            "MaxBotCount": 2
          }
        ],
        "Time_min": null,
        "Time_max": null,
        "RandomTimeSpawn": true,
        "OnlySpawnOnce": false,
        "BotZone": null
      },
      {
        "Name": "ZoneRedHouse PMC",
        "Bots": [
          {
            "BotType": "sptusec",
            "MaxBotCount": 1
          }
        ],
        "Time_min": 30,
        "Time_max": 50,
        "RandomTimeSpawn": false,
        "OnlySpawnOnce": false,
        "BotZone": "ZoneRedHouse"
      },
      {
        "Name": "ZoneRedHouse SCAV",
        "Bots": [
          {
            "BotType": "assault",
            "MaxBotCount": 2
          }
        ],
        "Time_min": 300,
        "Time_max": 600,
        "RandomTimeSpawn": false,
        "OnlySpawnOnce": false,
        "BotZone": "ZoneRedHouse"
      },
      {
        "Name": "ZoneRedHouse PMC",
        "Bots": [
          {
            "BotType": "assault",
            "MaxBotCount": 2
          }
        ],
        "Time_min": 700,
        "Time_max": 1100,
        "RandomTimeSpawn": false,
        "OnlySpawnOnce": false,
        "BotZone": "ZoneRedHouse"
      },
      {
        "Name": "ZoneRedHouse PMC",
        "Bots": [
          {
            "BotType": "sptusec",
            "MaxBotCount": 2
          }
        ],
        "Time_min": 1300,
        "Time_max": 1800,
        "RandomTimeSpawn": false,
        "OnlySpawnOnce": false,
        "BotZone": "ZoneRedHouse"
      },
      {
        "Name": "Late ZoneRedHouse SCAV",
        "Bots": [
          {
            "BotType": "assault",
            "MaxBotCount": 2
          }
        ],
        "Time_min": 2000,
        "Time_max": 3000,
        "RandomTimeSpawn": false,
        "OnlySpawnOnce": false,
        "BotZone": "ZoneRedHouse"
      },
      {
        "Name": "ZoneClearVill PMC",
        "Bots": [
          {
            "BotType": "sptusec",
            "MaxBotCount": 1
          }
        ],
        "Time_min": 30,
        "Time_max": 50,
        "RandomTimeSpawn": false,
        "OnlySpawnOnce": false,
        "BotZone": "ZoneClearVill"
      },
      {
        "Name": "ZoneClearVill SCAV",
        "Bots": [
          {
            "BotType": "sptusec",
            "MaxBotCount": 1
          }
        ],
        "Time_min": 300,
        "Time_max": 600,
        "RandomTimeSpawn": false,
        "OnlySpawnOnce": false,
        "BotZone": "ZoneClearVill"
      },
      {
        "Name": "ZoneClearVill PMC",
        "Bots": [
          {
            "BotType": "sptusec",
            "MaxBotCount": 2
          }
        ],
        "Time_min": 700,
        "Time_max": 1100,
        "RandomTimeSpawn": false,
        "OnlySpawnOnce": false,
        "BotZone": "ZoneClearVill"
      },
      {
        "Name": "ZoneClearVill PMC",
        "Bots": [
          {
            "BotType": "sptbear",
            "MaxBotCount": 1
          }
        ],
        "Time_min": 1400,
        "Time_max": 2000,
        "RandomTimeSpawn": false,
        "OnlySpawnOnce": false,
        "BotZone": "ZoneClearVill"
      },
      {
        "Name": "ZoneClearVill SCAV",
        "Bots": [
          {
            "BotType": "assault",
            "MaxBotCount": 1
          }
        ],
        "Time_min": 2800,
        "Time_max": 3500,
        "RandomTimeSpawn": false,
        "OnlySpawnOnce": false,
        "BotZone": "ZoneClearVill"
      },
      {
        "Name": "ZoneBrokenVill SCAV",
        "Bots": [
          {
            "BotType": "assault",
            "MaxBotCount": 1
          }
        ],
        "Time_min": 30,
        "Time_max": 50,
        "RandomTimeSpawn": false,
        "OnlySpawnOnce": false,
        "BotZone": "ZoneBrokenVill"
      },
      {
        "Name": "ZoneBrokenVill PMC",
        "Bots": [
          {
            "BotType": "sptbear",
            "MaxBotCount": 1
          }
        ],
        "Time_min": 300,
        "Time_max": 1000,
        "RandomTimeSpawn": false,
        "OnlySpawnOnce": false,
        "BotZone": "ZoneBrokenVill"
      },
      {
        "Name": "ZoneHouse PMC",
        "Bots": [
          {
            "BotType": "sptbear",
            "MaxBotCount": 1
          },
          {
            "BotType": "sptusec",
            "MaxBotCount": 1
          }
        ],
        "Time_min": 30,
        "Time_max": 50,
        "RandomTimeSpawn": false,
        "OnlySpawnOnce": false,
        "BotZone": "ZoneHouse"
      },
      {
        "Name": "ZoneHouse PMC",
        "Bots": [
          {
            "BotType": "sptbear",
            "MaxBotCount": 1
          },
          {
            "BotType": "sptusec",
            "MaxBotCount": 1
          }
        ],
        "Time_min": 300,
        "Time_max": 600,
        "RandomTimeSpawn": false,
        "OnlySpawnOnce": false,
        "BotZone": "ZoneHouse"
      },
      {
        "Name": "ZoneHouse PMC",
        "Bots": [
          {
            "BotType": "sptbear",
            "MaxBotCount": 1
          },
          {
            "BotType": "sptusec",
            "MaxBotCount": 1
          }
        ],
        "Time_min": 600,
        "Time_max": 1200,
        "RandomTimeSpawn": false,
        "OnlySpawnOnce": false,
        "BotZone": "ZoneHouse"
      },
      {
        "Name": "ZoneHouse PMC",
        "Bots": [
          {
            "BotType": "sptbear",
            "MaxBotCount": 1
          },
          {
            "BotType": "sptusec",
            "MaxBotCount": 1
          }
        ],
        "Time_min": 1200,
        "Time_max": 1800,
        "RandomTimeSpawn": false,
        "OnlySpawnOnce": false,
        "BotZone": "ZoneHouse"
      },
      {
        "Name": "ZoneHouse PMC",
        "Bots": [
          {
            "BotType": "sptbear",
            "MaxBotCount": 1
          },
          {
            "BotType": "sptusec",
            "MaxBotCount": 1
          }
        ],
        "Time_min": 1800,
        "Time_max": 2400,
        "RandomTimeSpawn": false,
        "OnlySpawnOnce": false,
        "BotZone": "ZoneHouse"
      },
      {
        "Name": "ZoneHouse PMC",
        "Bots": [
          {
            "BotType": "sptbear",
            "MaxBotCount": 1
          },
          {
            "BotType": "sptusec",
            "MaxBotCount": 1
          }
        ],
        "Time_min": 2400,
        "Time_max": 3000,
        "RandomTimeSpawn": false,
        "OnlySpawnOnce": false,
        "BotZone": "ZoneHouse"
      },
      {
        "Name": "ZoneHouse PMC",
        "Bots": [
          {
            "BotType": "sptbear",
            "MaxBotCount": 1
          }
        ],
        "Time_min": 3000,
        "Time_max": 3600,
        "RandomTimeSpawn": false,
        "OnlySpawnOnce": false,
        "BotZone": "ZoneHouse"
      },
      {
        "Name": "ZoneWoodCutter SCAV",
        "Bots": [
          {
            "BotType": "assault",
            "MaxBotCount": 2
          }
        ],
        "Time_min": 30,
        "Time_max": 50,
        "RandomTimeSpawn": false,
        "OnlySpawnOnce": false,
        "BotZone": "ZoneWoodCutter"
      },
      {
        "Name": "ZoneWoodCutter PMC",
        "Bots": [
          {
            "BotType": "sptusec",
            "MaxBotCount": 2
          }
        ],
        "Time_min": 300,
        "Time_max": 600,
        "RandomTimeSpawn": false,
        "OnlySpawnOnce": false,
        "BotZone": "ZoneWoodCutter"
      },
      {
        "Name": "ZoneWoodCutter PMC",
        "Bots": [
          {
            "BotType": "sptbear",
            "MaxBotCount": 2
          }
        ],
        "Time_min": 700,
        "Time_max": 1200,
        "RandomTimeSpawn": false,
        "OnlySpawnOnce": false,
        "BotZone": "ZoneWoodCutter"
      },
      {
        "Name": "ZoneWoodCutter PMC",
        "Bots": [
          {
            "BotType": "sptusec",
            "MaxBotCount": 2
          }
        ],
        "Time_min": 1400,
        "Time_max": 2000,
        "RandomTimeSpawn": false,
        "OnlySpawnOnce": false,
        "BotZone": "ZoneWoodCutter"
      },
      {
        "Name": "ZoneWoodCutter PMC",
        "Bots": [
          {
            "BotType": "sptusec",
            "MaxBotCount": 2
          }
        ],
        "Time_min": 2200,
        "Time_max": 2600,
        "RandomTimeSpawn": false,
        "OnlySpawnOnce": false,
        "BotZone": "ZoneWoodCutter"
      },
      {
        "Name": "ZoneWoodCutter PMC",
        "Bots": [
          {
            "BotType": "sptbear",
            "MaxBotCount": 2
          }
        ],
        "Time_min": 2700,
        "Time_max": 3600,
        "RandomTimeSpawn": false,
        "OnlySpawnOnce": false,
        "BotZone": "ZoneWoodCutter"
      },
      {
        "Name": "ZoneBigRocks PMC",
        "Bots": [
          {
            "BotType": "sptbear",
            "MaxBotCount": 1
          }
        ],
        "Time_min": 30,
        "Time_max": 50,
        "RandomTimeSpawn": false,
        "OnlySpawnOnce": false,
        "BotZone": "ZoneBigRocks"
      },
      {
        "Name": "ZoneRoad PMC",
        "Bots": [
          {
            "BotType": "sptbear",
            "MaxBotCount": 1
          }
        ],
        "Time_min": 30,
        "Time_max": 50,
        "RandomTimeSpawn": false,
        "OnlySpawnOnce": false,
        "BotZone": "ZoneRoad"
      },
      {
        "Name": "ZoneRoad SCAV",
        "Bots": [
          {
            "BotType": "assault",
            "MaxBotCount": 1
          }
        ],
        "Time_min": 1000,
        "Time_max": 1500,
        "RandomTimeSpawn": false,
        "OnlySpawnOnce": false,
        "BotZone": "ZoneRoad"
      },
      {
        "Name": "Late ZoneRoad PMC",
        "Bots": [
          {
            "BotType": "sptbear",
            "MaxBotCount": 1
          }
        ],
        "Time_min": 2000,
        "Time_max": 2400,
        "RandomTimeSpawn": false,
        "OnlySpawnOnce": false,
        "BotZone": "ZoneRoad"
      },
      {
        "Name": "Late ZoneRoad SCAV",
        "Bots": [
          {
            "BotType": "assault",
            "MaxBotCount": 1
          }
        ],
        "Time_min": 2500,
        "Time_max": 3300,
        "RandomTimeSpawn": false,
        "OnlySpawnOnce": false,
        "BotZone": "ZoneRoad"
      },
      {
        "Name": "ZoneHighRocks PMC",
        "Bots": [
          {
            "BotType": "sptusec",
            "MaxBotCount": 1
          }
        ],
        "Time_min": 30,
        "Time_max": 50,
        "RandomTimeSpawn": false,
        "OnlySpawnOnce": false,
        "BotZone": "ZoneHighRocks"
      },
      {
        "Name": "ZoneMiniHouse PMC",
        "Bots": [
          {
            "BotType": "sptbear",
            "MaxBotCount": 1
          }
        ],
        "Time_min": 30,
        "Time_max": 50,
        "RandomTimeSpawn": false,
        "OnlySpawnOnce": false,
        "BotZone": "ZoneMiniHouse"
      },
      {
        "Name": "ZoneBigRocks PMC",
        "Bots": [
          {
            "BotType": "sptusec",
            "MaxBotCount": 1
          }
        ],
        "Time_min": 30,
        "Time_max": 50,
        "RandomTimeSpawn": false,
        "OnlySpawnOnce": false,
        "BotZone": "ZoneBigRocks"
      }
    ],
    "MapBosses": [
      {
        "BossName": "bossknight",
        "BossEscortType": "exusec",
        "BossEscortAmount": "2",
        "Time": -1,
        "Supports": [
            {
                "BossEscortType": "followerbigpipe",
                "BossEscortAmount": "1"
            },
            {
                "BossEscortType": "followerbirdeye",
                "BossEscortAmount": "1"
            }
        ],
        "RandomTimeSpawn": true,
        "BossZone": "ZoneScavBase2",
        "OnlySpawnOnce": true
      },
      {
        "BossName": "bosskojaniy",
        "BossZone": "ZoneWoodCutter",
        "BossEscortType": "followerKojaniy",
        "BossEscortAmount": "2",
        "Time": -1,
        "Supports": null,
        "RandomTimeSpawn": false,
        "OnlySpawnOnce": true
      }
    ]
  }
]
