{
  "Locations": [
    {
      "MapName": "lighthouse",
      "GroupNum": 30,
      "Name": "TreatmentBeachBoss",
      "Position": {
        "x": 52.67717,
        "y": 8.201275,
        "z": -647.04895
      },
      "WildSpawnType": "followerbigpipe",
      "MinDistance": 1.0,
      "MaxDistance": 1.0,
      "BotTriggerDistance": 60.0,
      "BotTimerTrigger": 10000.0,
      "MaxRandomNumBots": 1,
      "SpawnChance": 100,
      "MaxSpawnsBeforeCoolDown": 1,
      "IgnoreTimerFirstSpawn": true,
      "MinSpawnDistanceFromPlayer": 20
    },
    {
      "MapName": "lighthouse",
      "GroupNum": 31,
      "Name": "TreatmentContainerBoss",
      "Position": {
        "x": -64.78216,
        "y": 5.05027628,
        "z": -733.9895
      },
      "WildSpawnType": "bossknight",
      "MinDistance": 1.0,
      "MaxDistance": 1.0,
      "BotTriggerDistance": 40.0,
      "BotTimerTrigger": 10000.0,
      "MaxRandomNumBots": 1,
      "SpawnChance": 100,
      "MaxSpawnsBeforeCoolDown": 1,
      "IgnoreTimerFirstSpawn": true,
      "MinSpawnDistanceFromPlayer": 20
    },
    {
      "MapName": "lighthouse",
      "GroupNum": 32,
      "Name": "TreatmentRockBoss",
      "Position": {
        "x": -177.93927,
        "y": 8.201271,
        "z": -641.771057
      },
      "WildSpawnType": "followerbirdeye",
      "MinDistance": 1.0,
      "MaxDistance": 1.0,
      "BotTriggerDistance": 60.0,
      "BotTimerTrigger": 4500.0,
      "MaxRandomNumBots": 1,
      "SpawnChance": 100,
      "MaxSpawnsBeforeCoolDown": 1,
      "IgnoreTimerFirstSpawn": true,
      "MinSpawnDistanceFromPlayer": 20.0
    }
  ]
}
