{
  "Locations": [
    {
      "MapName": "tarkovstreets",
      "GroupNum": 50,
      "Name": "Construc Sparja",
      "Position": {
        "x": 156.29361,
        "y": 3.75064373,
        "z": 293.1533
      },
      "WildSpawnType": "assault",
      "MinDistance": 1,
      "MaxDistance": 1,
      "BotTriggerDistance": 300,
      "BotTimerTrigger": 240,
      "MaxRandomNumBots": 1,
      "SpawnChance": 30,
      "MaxSpawnsBeforeCoolDown": 2,
      "IgnoreTimerFirstSpawn": false,
      "MinSpawnDistanceFromPlayer": 60
    },
    {
      "MapName": "tarkovstreets",
      "GroupNum": 50,
      "Name": "streets scav",
      "Position": {
        "x": 124.271912,
        "y": -2.219596,
        "z": 62.33575
      },
      "WildSpawnType": "assault",
      "MinDistance": 1,
      "MaxDistance": 1,
      "BotTriggerDistance": 300,
      "BotTimerTrigger": 180,
      "MaxRandomNumBots": 1,
      "SpawnChance": 30,
      "MaxSpawnsBeforeCoolDown": 2,
      "IgnoreTimerFirstSpawn": false,
      "MinSpawnDistanceFromPlayer": 60
    },
    {
      "MapName": "tarkovstreets",
      "GroupNum": 50,
      "Name": "streets scav",
      "Position": {
        "x": 123.135918,
        "y": 4.49726725,
        "z": 145.6643
      },
      "WildSpawnType": "assault",
      "MinDistance": 1,
      "MaxDistance": 1,
      "BotTriggerDistance": 300,
      "BotTimerTrigger": 160,
      "MaxRandomNumBots": 1,
      "SpawnChance": 30,
      "MaxSpawnsBeforeCoolDown": 2,
      "IgnoreTimerFirstSpawn": false,
      "MinSpawnDistanceFromPlayer": 60
    },
    {
      "MapName": "tarkovstreets",
      "GroupNum": 50,
      "Name": "streets scav",
      "Position": {
        "x": -55.73635,
        "y": 1.4155153,
        "z": 157.3048
      },
      "WildSpawnType": "assault",
      "MinDistance": 1,
      "MaxDistance": 1,
      "BotTriggerDistance": 300,
      "BotTimerTrigger": 200,
      "MaxRandomNumBots": 1,
      "SpawnChance": 30,
      "MaxSpawnsBeforeCoolDown": 2,
      "IgnoreTimerFirstSpawn": false,
      "MinSpawnDistanceFromPlayer": 60
    },
    {
      "MapName": "tarkovstreets",
      "GroupNum": 50,
      "Name": "streets scav",
      "Position": {
        "x": -172.414413,
        "y": 6.066414,
        "z": 226.924545
      },
      "WildSpawnType": "assault",
      "MinDistance": 1,
      "MaxDistance": 1,
      "BotTriggerDistance": 300,
      "BotTimerTrigger": 230,
      "MaxRandomNumBots": 1,
      "SpawnChance": 30,
      "MaxSpawnsBeforeCoolDown": 2,
      "IgnoreTimerFirstSpawn": false,
      "MinSpawnDistanceFromPlayer": 60
    },
    {
      "MapName": "tarkovstreets",
      "GroupNum": 50,
      "Name": "streets scav",
      "Position": {
        "x": 92.3770447,
        "y": 2.63761854,
        "z": 276.906128
      },
      "WildSpawnType": "assault",
      "MinDistance": 1,
      "MaxDistance": 1,
      "BotTriggerDistance": 300,
      "BotTimerTrigger": 260,
      "MaxRandomNumBots": 1,
      "SpawnChance": 30,
      "MaxSpawnsBeforeCoolDown": 2,
      "IgnoreTimerFirstSpawn": false,
      "MinSpawnDistanceFromPlayer": 60
    },
    {
      "MapName": "tarkovstreets",
      "GroupNum": 51,
      "Name": "scav",
      "Position": {
        "x": -153.026184,
        "y": 8.612602,
        "z": 399.513977
      },
      "WildSpawnType": "assault",
      "MinDistance": 1,
      "MaxDistance": 1,
      "BotTriggerDistance": 300,
      "BotTimerTrigger": 160,
      "MaxRandomNumBots": 2,
      "SpawnChance": 30,
      "MaxSpawnsBeforeCoolDown": 2,
      "IgnoreTimerFirstSpawn": false,
      "MinSpawnDistanceFromPlayer": 60
    },
    {
      "MapName": "tarkovstreets",
      "GroupNum": 51,
      "Name": "scav",
      "Position": {
        "x": -17.8972359,
        "y": 0.9133898,
        "z": 401.566071
      },
      "WildSpawnType": "assault",
      "MinDistance": 1,
      "MaxDistance": 1,
      "BotTriggerDistance": 300,
      "BotTimerTrigger": 220,
      "MaxRandomNumBots": 2,
      "SpawnChance": 30,
      "MaxSpawnsBeforeCoolDown": 2,
      "IgnoreTimerFirstSpawn": false,
      "MinSpawnDistanceFromPlayer": 60
    },
    {
      "MapName": "tarkovstreets",
      "GroupNum": 51,
      "Name": "scav",
      "Position": {
        "x": 5.261718,
        "y": 2.11363435,
        "z": 360.66925
      },
      "WildSpawnType": "assault",
      "MinDistance": 1,
      "MaxDistance": 1,
      "BotTriggerDistance": 300,
      "BotTimerTrigger": 240,
      "MaxRandomNumBots": 1,
      "SpawnChance": 30,
      "MaxSpawnsBeforeCoolDown": 2,
      "IgnoreTimerFirstSpawn": true,
      "MinSpawnDistanceFromPlayer": 60
    },
    {
      "MapName": "tarkovstreets",
      "GroupNum": 51,
      "Name": "scav",
      "Position": {
        "x": 104.709114,
        "y": 3.24114561,
        "z": 386.05545
      },
      "WildSpawnType": "assault",
      "MinDistance": 1,
      "MaxDistance": 1,
      "BotTriggerDistance": 300,
      "BotTimerTrigger": 240,
      "MaxRandomNumBots": 1,
      "SpawnChance": 30,
      "MaxSpawnsBeforeCoolDown": 2,
      "IgnoreTimerFirstSpawn": true,
      "MinSpawnDistanceFromPlayer": 60
    },
    {
      "MapName": "tarkovstreets",
      "GroupNum": 51,
      "Name": "scav",
      "Position": {
        "x": 160.149323,
        "y": 3.3326745,
        "z": 338.474884
      },
      "WildSpawnType": "assault",
      "MinDistance": 1,
      "MaxDistance": 1,
      "BotTriggerDistance": 300,
      "BotTimerTrigger": 240,
      "MaxRandomNumBots": 1,
      "SpawnChance": 30,
      "MaxSpawnsBeforeCoolDown": 2,
      "IgnoreTimerFirstSpawn": true,
      "MinSpawnDistanceFromPlayer": 60
    },
    {
      "MapName": "tarkovstreets",
      "GroupNum": 52,
      "Name": "scav",
      "Position": {
        "x": 250.056976,
        "y": 3.33356953,
        "z": 380.708679
      },
      "WildSpawnType": "assault",
      "MinDistance": 1,
      "MaxDistance": 1,
      "BotTriggerDistance": 300,
      "BotTimerTrigger": 240,
      "MaxRandomNumBots": 1,
      "SpawnChance": 30,
      "MaxSpawnsBeforeCoolDown": 2,
      "IgnoreTimerFirstSpawn": true,
      "MinSpawnDistanceFromPlayer": 60
    },
    {
      "MapName": "tarkovstreets",
      "GroupNum": 52,
      "Name": "scav",
      "Position": {
        "x": 232.332489,
        "y": -1.25006688,
        "z": 373.507538
      },
      "WildSpawnType": "assault",
      "MinDistance": 1,
      "MaxDistance": 1,
      "BotTriggerDistance": 300,
      "BotTimerTrigger": 300,
      "MaxRandomNumBots": 2,
      "SpawnChance": 30,
      "MaxSpawnsBeforeCoolDown": 2,
      "IgnoreTimerFirstSpawn": false,
      "MinSpawnDistanceFromPlayer": 60
    },
    {
      "MapName": "tarkovstreets",
      "GroupNum": 52,
      "Name": "scav",
      "Position": {
        "x": 189.851273,
        "y": 3.41835785,
        "z": 320.476685
      },
      "WildSpawnType": "assault",
      "MinDistance": 1,
      "MaxDistance": 1,
      "BotTriggerDistance": 300,
      "BotTimerTrigger": 350,
      "MaxRandomNumBots": 1,
      "SpawnChance": 30,
      "MaxSpawnsBeforeCoolDown": 2,
      "IgnoreTimerFirstSpawn": false,
      "MinSpawnDistanceFromPlayer": 60
    },
    {
      "MapName": "tarkovstreets",
      "GroupNum": 52,
      "Name": "scav",
      "Position": {
        "x": 206.2159,
        "y": 3.92399788,
        "z": 303.932281
      },
      "WildSpawnType": "assault",
      "MinDistance": 1,
      "MaxDistance": 1,
      "BotTriggerDistance": 300,
      "BotTimerTrigger": 400,
      "MaxRandomNumBots": 2,
      "SpawnChance": 30,
      "MaxSpawnsBeforeCoolDown": 2,
      "IgnoreTimerFirstSpawn": false,
      "MinSpawnDistanceFromPlayer": 60
    },
    {
      "MapName": "tarkovstreets",
      "GroupNum": 52,
      "Name": "scav",
      "Position": {
        "x": 18.0056515,
        "y": 2.16833639,
        "z": 215.390182
      },
      "WildSpawnType": "assault",
      "MinDistance": 1,
      "MaxDistance": 1,
      "BotTriggerDistance": 300,
      "BotTimerTrigger": 290,
      "MaxRandomNumBots": 2,
      "SpawnChance": 30,
      "MaxSpawnsBeforeCoolDown": 2,
      "IgnoreTimerFirstSpawn": false,
      "MinSpawnDistanceFromPlayer": 60
    },
    {
      "MapName": "tarkovstreets",
      "GroupNum": 53,
      "Name": "scav",
      "Position": {
        "x": 61.9528465,
        "y": 2.57886457,
        "z": 287.1624
      },
      "WildSpawnType": "assault",
      "MinDistance": 1,
      "MaxDistance": 1,
      "BotTriggerDistance": 300,
      "BotTimerTrigger": 310,
      "MaxRandomNumBots": 2,
      "SpawnChance": 30,
      "MaxSpawnsBeforeCoolDown": 2,
      "IgnoreTimerFirstSpawn": false,
      "MinSpawnDistanceFromPlayer": 60
    },
    {
      "MapName": "tarkovstreets",
      "GroupNum": 53,
      "Name": "scav",
      "Position": {
        "x": 77.07757,
        "y": 2.55629849,
        "z": 301.570679
      },
      "WildSpawnType": "assault",
      "MinDistance": 1,
      "MaxDistance": 1,
      "BotTriggerDistance": 300,
      "BotTimerTrigger": 220,
      "MaxRandomNumBots": 1,
      "SpawnChance": 30,
      "MaxSpawnsBeforeCoolDown": 2,
      "IgnoreTimerFirstSpawn": false,
      "MinSpawnDistanceFromPlayer": 60
    },
    {
      "MapName": "tarkovstreets",
      "GroupNum": 53,
      "Name": "scav",
      "Position": {
        "x": -97.63822,
        "y": 5.04110861,
        "z": 62.654274
      },
      "WildSpawnType": "assault",
      "MinDistance": 1,
      "MaxDistance": 1,
      "BotTriggerDistance": 300,
      "BotTimerTrigger": 200,
      "MaxRandomNumBots": 1,
      "SpawnChance": 30,
      "MaxSpawnsBeforeCoolDown": 2,
      "IgnoreTimerFirstSpawn": false,
      "MinSpawnDistanceFromPlayer": 60
    },
    {
      "MapName": "tarkovstreets",
      "GroupNum": 53,
      "Name": "scav",
      "Position": {
        "x": -67.4353256,
        "y": 0.933495164,
        "z": 117.00882
      },
      "WildSpawnType": "assault",
      "MinDistance": 1,
      "MaxDistance": 1,
      "BotTriggerDistance": 300,
      "BotTimerTrigger": 180,
      "MaxRandomNumBots": 2,
      "SpawnChance": 30,
      "MaxSpawnsBeforeCoolDown": 2,
      "IgnoreTimerFirstSpawn": false,
      "MinSpawnDistanceFromPlayer": 60
    },
    {
      "MapName": "tarkovstreets",
      "GroupNum": 53,
      "Name": "scav",
      "Position": {
        "x": -87.32377,
        "y": 2.197751,
        "z": 297.287
      },
      "WildSpawnType": "assault",
      "MinDistance": 1,
      "MaxDistance": 1,
      "BotTriggerDistance": 300,
      "BotTimerTrigger": 180,
      "MaxRandomNumBots": 1,
      "SpawnChance": 30,
      "MaxSpawnsBeforeCoolDown": 2,
      "IgnoreTimerFirstSpawn": false,
      "MinSpawnDistanceFromPlayer": 60
    },
    {
      "MapName": "tarkovstreets",
      "GroupNum": 53,
      "Name": "scav",
      "Position": {
        "x": 66.0016861,
        "y": 0.3661974,
        "z": 124.907639
      },
      "WildSpawnType": "assault",
      "MinDistance": 1,
      "MaxDistance": 1,
      "BotTriggerDistance": 300,
      "BotTimerTrigger": 300,
      "MaxRandomNumBots": 2,
      "SpawnChance": 30,
      "MaxSpawnsBeforeCoolDown": 2,
      "IgnoreTimerFirstSpawn": true,
      "MinSpawnDistanceFromPlayer": 60
    },
    {
      "MapName": "tarkovstreets",
      "GroupNum": 54,
      "Name": "scav",
      "Position": {
        "x": 110.489738,
        "y": 0.936501265,
        "z": 155.374527
      },
      "WildSpawnType": "assault",
      "MinDistance": 1,
      "MaxDistance": 1,
      "BotTriggerDistance": 300,
      "BotTimerTrigger": 320,
      "MaxRandomNumBots": 1,
      "SpawnChance": 30,
      "MaxSpawnsBeforeCoolDown": 2,
      "IgnoreTimerFirstSpawn": true,
      "MinSpawnDistanceFromPlayer": 60
    },
    {
      "MapName": "tarkovstreets",
      "GroupNum": 54,
      "Name": "scav",
      "Position": {
        "x": 133.318344,
        "y": -0.117149048,
        "z": 126.059288
      },
      "WildSpawnType": "assault",
      "MinDistance": 1,
      "MaxDistance": 1,
      "BotTriggerDistance": 300,
      "BotTimerTrigger": 275,
      "MaxRandomNumBots": 1,
      "SpawnChance": 30,
      "MaxSpawnsBeforeCoolDown": 2,
      "IgnoreTimerFirstSpawn": false,
      "MinSpawnDistanceFromPlayer": 60
    },
    {
      "MapName": "tarkovstreets",
      "GroupNum": 54,
      "Name": "scav_pinewood",
      "Position": {
        "x": -70.39301,
        "y": 0.9332268,
        "z": 113.164452
      },
      "WildSpawnType": "assault",
      "MinDistance": 1,
      "MaxDistance": 1,
      "BotTriggerDistance": 300,
      "BotTimerTrigger": 250,
      "MaxRandomNumBots": 1,
      "SpawnChance": 30,
      "MaxSpawnsBeforeCoolDown": 2,
      "IgnoreTimerFirstSpawn": false,
      "MinSpawnDistanceFromPlayer": 60
    },
    {
      "MapName": "tarkovstreets",
      "GroupNum": 54,
      "Name": "scav_sparja",
      "Position": {
        "x": -58.50139,
        "y": 1.38301682,
        "z": 174.145508
      },
      "WildSpawnType": "assault",
      "MinDistance": 1,
      "MaxDistance": 1,
      "BotTriggerDistance": 300,
      "BotTimerTrigger": 300,
      "MaxRandomNumBots": 1,
      "SpawnChance": 30,
      "MaxSpawnsBeforeCoolDown": 2,
      "IgnoreTimerFirstSpawn": false,
      "MinSpawnDistanceFromPlayer": 60
    },
    {
      "MapName": "tarkovstreets",
      "GroupNum": 55,
      "Name": "scav_road_crash",
      "Position": {
        "x": 17.2708645,
        "y": 2.47931385,
        "z": 241.893387
      },
      "WildSpawnType": "assault",
      "MinDistance": 1,
      "MaxDistance": 1,
      "BotTriggerDistance": 300,
      "BotTimerTrigger": 280,
      "MaxRandomNumBots": 1,
      "SpawnChance": 30,
      "MaxSpawnsBeforeCoolDown": 2,
      "IgnoreTimerFirstSpawn": false,
      "MinSpawnDistanceFromPlayer": 60
    },
    {
      "MapName": "tarkovstreets",
      "GroupNum": 55,
      "Name": "scav_bectn",
      "Position": {
        "x": -129.027954,
        "y": 2.197756,
        "z": 325.653473
      },
      "WildSpawnType": "assault",
      "MinDistance": 1,
      "MaxDistance": 1,
      "BotTriggerDistance": 300,
      "BotTimerTrigger": 330,
      "MaxRandomNumBots": 2,
      "SpawnChance": 30,
      "MaxSpawnsBeforeCoolDown": 2,
      "IgnoreTimerFirstSpawn": true,
      "MinSpawnDistanceFromPlayer": 60
    },
    {
      "MapName": "tarkovstreets",
      "GroupNum": 56,
      "Name": "new streets scav",
      "Position": {
        "x": 139.395,
        "y": -1.87310374,
        "z": -132.435532
      },
      "WildSpawnType": "assault",
      "MinDistance": 1,
      "MaxDistance": 1,
      "BotTriggerDistance": 300,
      "BotTimerTrigger": 300,
      "MaxRandomNumBots": 1,
      "SpawnChance": 30,
      "MaxSpawnsBeforeCoolDown": 2,
      "IgnoreTimerFirstSpawn": false,
      "MinSpawnDistanceFromPlayer": 60
    },
    {
      "MapName": "tarkovstreets",
      "GroupNum": 56,
      "Name": "new streets scav",
      "Position": {
        "x": 71.28389,
        "y": -0.1627128,
        "z": -53.43159
      },
      "WildSpawnType": "assault",
      "MinDistance": 1,
      "MaxDistance": 1,
      "BotTriggerDistance": 300,
      "BotTimerTrigger": 300,
      "MaxRandomNumBots": 1,
      "SpawnChance": 30,
      "MaxSpawnsBeforeCoolDown": 2,
      "IgnoreTimerFirstSpawn": false,
      "MinSpawnDistanceFromPlayer": 60
    },
    {
      "MapName": "tarkovstreets",
      "GroupNum": 57,
      "Name": "new streets scav",
      "Position": {
        "x": -50.4019547,
        "y": 5.099989,
        "z": -55.3072739
      },
      "WildSpawnType": "assault",
      "MinDistance": 1,
      "MaxDistance": 1,
      "BotTriggerDistance": 300,
      "BotTimerTrigger": 300,
      "MaxRandomNumBots": 1,
      "SpawnChance": 30,
      "MaxSpawnsBeforeCoolDown": 2,
      "IgnoreTimerFirstSpawn": true,
      "MinSpawnDistanceFromPlayer": 60
    },
    {
      "MapName": "tarkovstreets",
      "GroupNum": 57,
      "Name": "new streets scav",
      "Position": {
        "x": -77.9079056,
        "y": 0.6011249,
        "z": -45.3268776
      },
      "WildSpawnType": "assault",
      "MinDistance": 1,
      "MaxDistance": 1,
      "BotTriggerDistance": 300,
      "BotTimerTrigger": 300,
      "MaxRandomNumBots": 1,
      "SpawnChance": 30,
      "MaxSpawnsBeforeCoolDown": 2,
      "IgnoreTimerFirstSpawn": true,
      "MinSpawnDistanceFromPlayer": 60
    },
    {
      "MapName": "tarkovstreets",
      "GroupNum": 58,
      "Name": "new streets scav",
      "Position": {
        "x": -149.595978,
        "y": 9.599995,
        "z": -20.9252434
      },
      "WildSpawnType": "assault",
      "MinDistance": 1,
      "MaxDistance": 1,
      "BotTriggerDistance": 300,
      "BotTimerTrigger": 300,
      "MaxRandomNumBots": 1,
      "SpawnChance": 30,
      "MaxSpawnsBeforeCoolDown": 2,
      "IgnoreTimerFirstSpawn": false,
      "MinSpawnDistanceFromPlayer": 60
    },
    {
      "MapName": "tarkovstreets",
      "GroupNum": 58,
      "Name": "new streets scav",
      "Position": {
        "x": 255.575653,
        "y": -1.46606469,
        "z": 120.947853
      },
      "WildSpawnType": "assault",
      "MinDistance": 1,
      "MaxDistance": 1,
      "BotTriggerDistance": 300,
      "BotTimerTrigger": 300,
      "MaxRandomNumBots": 1,
      "SpawnChance": 30,
      "MaxSpawnsBeforeCoolDown": 2,
      "IgnoreTimerFirstSpawn": false,
      "MinSpawnDistanceFromPlayer": 60
    },
    {
      "MapName": "tarkovstreets",
      "GroupNum": 59,
      "Name": "new streets scav",
      "Position": {
        "x": 236.318863,
        "y": -5.82236338,
        "z": 26.13757
      },
      "WildSpawnType": "assault",
      "MinDistance": 1,
      "MaxDistance": 1,
      "BotTriggerDistance": 300,
      "BotTimerTrigger": 300,
      "MaxRandomNumBots": 1,
      "SpawnChance": 30,
      "MaxSpawnsBeforeCoolDown": 2,
      "IgnoreTimerFirstSpawn": true,
      "MinSpawnDistanceFromPlayer": 60
    }
  ]
}
