{
  "MapName": "laboratory",
  "Zones": {
    "Zone_Red": [
      {
        "x": -259.0605,
        "y": 0.009293522,
        "z": -388.4793
      }
    ],
    "Zone_Red_Parking": [
      {
        "x": -220.992188,
        "y": 0.0228912737,
        "z": -405.46048
      }
    ],
    "Zone_Red_Infirmary": [
      {
        "x": -132.094391,
        "y": 0.0368003175,
        "z": -417.220337
      },
      {
        "x": -117.814316,
        "y": 0.008905247,
        "z": -381.562
      }
    ],
    "Zone_RedGreen_BlackRoom": [
      {
        "x": -134.64534,
        "y": 0.008891797,
        "z": -343.9739
      }
    ],
    "Zone_Green_Servers_PMC_Start": [
      {
        "x": -127.087746,
        "y": 1.36848688,
        "z": -314.859253
      },
      {
        "x": -133.65802,
        "y": 4.10687542,
        "z": -284.917175
      }
    ],
    "Zone_Green_Gym_PMC_Start": [
      {
        "x": -224.5817,
        "y": 0.07067463,
        "z": -280.653229
      },
      {
        "x": -235.9631,
        "y": 0.02021411,
        "z": -301.364746
      }
    ],
    "Zone_Orange_SouthHalls_PMC_Start": [
      {
        "x": -117.577316,
        "y": 4.09994268,
        "z": -352.15094
      },
      {
        "x": -118.201469,
        "y": 4.10003853,
        "z": -406.457977
      }
    ],
    "Zone_Orange_Offices_PMC_Start": [
      {
        "x": -162.7386,
        "y": 4.100834,
        "z": -414.788055
      },
      {
        "x": -180.121933,
        "y": 4.10083342,
        "z": -415.823547
      }
    ],
    "Zone_Yellow_Sewers_PMC_Start": [
      {
        "x": -157.940536,
        "y": -4.025572,
        "z": -322.816437
      }
    ],
    "Zone_Yellow_Hallways_PMC_Start": [
      {
        "x": -141.633255,
        "y": -4.053967,
        "z": -362.562347
      }
    ],
    "Zone_Blue_West_PMC_Start": [
      {
        "x": -266.167267,
        "y": -4.050967,
        "z": -331.420319
      },
      {
        "x": -246.118454,
        "y": -4.050969,
        "z": -315.094421
      }
    ]
  }
}